skonnxrt/__init__.py
skonnxrt/helpers/__init__.py
skonnxrt/helpers/onnx_helper.py
skonnxrt/sklapi/__init__.py
skonnxrt/sklapi/onnx_transformer.py
scikit_onnxruntime-0.2.1.4.dist-info/LICENSE
scikit_onnxruntime-0.2.1.4.dist-info/METADATA
scikit_onnxruntime-0.2.1.4.dist-info/WHEEL
scikit_onnxruntime-0.2.1.4.dist-info/top_level.txt
scikit_onnxruntime-0.2.1.4.dist-info/RECORD
