Metadata-Version: 2.1
Name: scikit-onnxruntime
Version: 0.2.1.4
Summary: Scikit-learn wrapper of onnxruntime
Home-page: https://github.com/xadupre/scikit-onnxruntime
Author: Microsoft Corporation
Author-email: xadupre@microsoft.com
License: MIT License
Platform: UNKNOWN
Classifier: Development Status :: 4 - Beta
Classifier: Environment :: Console
Classifier: Intended Audience :: Developers
Classifier: Operating System :: MacOS :: MacOS X
Classifier: Operating System :: Microsoft :: Windows
Classifier: Programming Language :: Python
Classifier: Programming Language :: Python :: 3.5
Classifier: Programming Language :: Python :: 3.6
Classifier: Programming Language :: Python :: 3.7
Classifier: License :: OSI Approved :: MIT License
Requires-Dist: onnx
Requires-Dist: onnxruntime
Requires-Dist: pandas
Requires-Dist: scikit-learn
